{
  "generated_at": "2026-06-08T18:31:05Z",
  "source_file": "data/threat_ips.json",
  "total_ips_analyzed": 19,
  "unique_asns": 12,
  "top_attack_asns": [
    {
      "asn": "AS396982",
      "asn_name": "Google LLC",
      "ip_count": 4,
      "risk_tier": "MEDIUM",
      "anon_count": 0
    },
    {
      "asn": "AS8075",
      "asn_name": "Microsoft Corporation",
      "ip_count": 3,
      "risk_tier": "HIGH",
      "anon_count": 0
    },
    {
      "asn": "AS398324",
      "asn_name": "Censys, Inc.",
      "ip_count": 2,
      "risk_tier": "HIGH",
      "anon_count": 0
    },
    {
      "asn": "AS213412",
      "asn_name": "ONYPHE SAS",
      "ip_count": 2,
      "risk_tier": "HIGH",
      "anon_count": 0
    },
    {
      "asn": "AS63949",
      "asn_name": "Akamai Connected Cloud",
      "ip_count": 1,
      "risk_tier": "HIGH",
      "anon_count": 0
    },
    {
      "asn": "AS4766",
      "asn_name": "Korea Telecom",
      "ip_count": 1,
      "risk_tier": "HIGH",
      "anon_count": 0
    },
    {
      "asn": "AS17621",
      "asn_name": "China Unicom Shanghai network",
      "ip_count": 1,
      "risk_tier": "HIGH",
      "anon_count": 0
    },
    {
      "asn": "AS133542",
      "asn_name": "Net Vision",
      "ip_count": 1,
      "risk_tier": "MEDIUM",
      "anon_count": 0
    },
    {
      "asn": "AS7713",
      "asn_name": "PT Telekomunikasi Indonesia",
      "ip_count": 1,
      "risk_tier": "LOW",
      "anon_count": 0
    },
    {
      "asn": "AS14061",
      "asn_name": "DigitalOcean, LLC",
      "ip_count": 1,
      "risk_tier": "HIGH",
      "anon_count": 0
    }
  ],
  "high_risk_asns": [
    {
      "asn": "AS8075",
      "asn_name": "Microsoft Corporation",
      "ip_count": 3,
      "risk_tier": "HIGH",
      "anon_count": 0
    },
    {
      "asn": "AS398324",
      "asn_name": "Censys, Inc.",
      "ip_count": 2,
      "risk_tier": "HIGH",
      "anon_count": 0
    },
    {
      "asn": "AS213412",
      "asn_name": "ONYPHE SAS",
      "ip_count": 2,
      "risk_tier": "HIGH",
      "anon_count": 0
    },
    {
      "asn": "AS63949",
      "asn_name": "Akamai Connected Cloud",
      "ip_count": 1,
      "risk_tier": "HIGH",
      "anon_count": 0
    },
    {
      "asn": "AS4766",
      "asn_name": "Korea Telecom",
      "ip_count": 1,
      "risk_tier": "HIGH",
      "anon_count": 0
    },
    {
      "asn": "AS17621",
      "asn_name": "China Unicom Shanghai network",
      "ip_count": 1,
      "risk_tier": "HIGH",
      "anon_count": 0
    },
    {
      "asn": "AS14061",
      "asn_name": "DigitalOcean, LLC",
      "ip_count": 1,
      "risk_tier": "HIGH",
      "anon_count": 0
    },
    {
      "asn": "AS150436",
      "asn_name": "Byteplus Pte. Ltd.",
      "ip_count": 1,
      "risk_tier": "HIGH",
      "anon_count": 0
    },
    {
      "asn": "AS45102",
      "asn_name": "Alibaba (US) Technology Co., Ltd.",
      "ip_count": 1,
      "risk_tier": "HIGH",
      "anon_count": 0
    }
  ],
  "anon_infrastructure": [],
  "country_summary": [
    {
      "country": "US",
      "code": "",
      "count": 7
    },
    {
      "country": "BE",
      "code": "",
      "count": 4
    },
    {
      "country": "IN",
      "code": "",
      "count": 1
    },
    {
      "country": "SG",
      "code": "",
      "count": 1
    },
    {
      "country": "JP",
      "code": "",
      "count": 1
    },
    {
      "country": "KR",
      "code": "",
      "count": 1
    },
    {
      "country": "HK",
      "code": "",
      "count": 1
    },
    {
      "country": "CN",
      "code": "",
      "count": 1
    },
    {
      "country": "BD",
      "code": "",
      "count": 1
    },
    {
      "country": "ID",
      "code": "",
      "count": 1
    }
  ],
  "clusters": [
    {
      "asn": "AS396982",
      "asn_name": "Google LLC",
      "ip_count": 4,
      "unique_ips": [
        "198.235.24.212",
        "34.76.199.172",
        "34.78.140.9",
        "35.195.250.46"
      ],
      "countries": [
        "BE"
      ],
      "top_country": "BE",
      "avg_abuse_score": 62.5,
      "max_abuse_score": 86,
      "total_reports": 0,
      "tor_count": 0,
      "proxy_count": 0,
      "vpn_count": 0,
      "anon_count": 0,
      "high_risk_count": 0,
      "critical_count": 0,
      "risk_tier": "MEDIUM",
      "tags": [
        "cloud-provider"
      ],
      "first_seen": "2026-06-08T18:30:56Z",
      "last_seen": "2026-06-08T18:31:03Z",
      "isps": [
        "Google LLC",
        "Palo Alto Networks, Inc"
      ]
    },
    {
      "asn": "AS8075",
      "asn_name": "Microsoft Corporation",
      "ip_count": 3,
      "unique_ips": [
        "145.132.103.23",
        "20.65.195.62",
        "20.81.140.174"
      ],
      "countries": [
        "US"
      ],
      "top_country": "US",
      "avg_abuse_score": 100,
      "max_abuse_score": 100,
      "total_reports": 0,
      "tor_count": 0,
      "proxy_count": 0,
      "vpn_count": 0,
      "anon_count": 0,
      "high_risk_count": 0,
      "critical_count": 0,
      "risk_tier": "HIGH",
      "tags": [
        "high-abuse"
      ],
      "first_seen": "2026-06-08T18:30:56Z",
      "last_seen": "2026-06-08T18:31:04Z",
      "isps": [
        "Microsoft Corporation",
        "Microsoft Limited"
      ]
    },
    {
      "asn": "AS398324",
      "asn_name": "Censys, Inc.",
      "ip_count": 2,
      "unique_ips": [
        "66.132.186.172",
        "66.132.195.58"
      ],
      "countries": [
        "US"
      ],
      "top_country": "US",
      "avg_abuse_score": 100,
      "max_abuse_score": 100,
      "total_reports": 0,
      "tor_count": 0,
      "proxy_count": 0,
      "vpn_count": 0,
      "anon_count": 0,
      "high_risk_count": 0,
      "critical_count": 0,
      "risk_tier": "HIGH",
      "tags": [
        "high-abuse"
      ],
      "first_seen": "2026-06-08T18:30:56Z",
      "last_seen": "2026-06-08T18:31:00Z",
      "isps": [
        "Censys, Inc."
      ]
    },
    {
      "asn": "AS213412",
      "asn_name": "ONYPHE SAS",
      "ip_count": 2,
      "unique_ips": [
        "91.230.168.136",
        "91.230.168.190"
      ],
      "countries": [
        "US"
      ],
      "top_country": "US",
      "avg_abuse_score": 100,
      "max_abuse_score": 100,
      "total_reports": 0,
      "tor_count": 0,
      "proxy_count": 0,
      "vpn_count": 0,
      "anon_count": 0,
      "high_risk_count": 0,
      "critical_count": 0,
      "risk_tier": "HIGH",
      "tags": [
        "high-abuse"
      ],
      "first_seen": "2026-06-08T18:30:56Z",
      "last_seen": "2026-06-08T18:31:04Z",
      "isps": [
        "FR ONYPHE"
      ]
    },
    {
      "asn": "AS63949",
      "asn_name": "Akamai Connected Cloud",
      "ip_count": 1,
      "unique_ips": [
        "172.104.93.159"
      ],
      "countries": [
        "JP"
      ],
      "top_country": "JP",
      "avg_abuse_score": 100,
      "max_abuse_score": 100,
      "total_reports": 0,
      "tor_count": 0,
      "proxy_count": 0,
      "vpn_count": 0,
      "anon_count": 0,
      "high_risk_count": 0,
      "critical_count": 0,
      "risk_tier": "HIGH",
      "tags": [
        "high-abuse",
        "cloud-provider"
      ],
      "first_seen": "2026-06-08T18:30:57Z",
      "last_seen": "2026-06-08T18:30:57Z",
      "isps": [
        "Linode"
      ]
    },
    {
      "asn": "AS4766",
      "asn_name": "Korea Telecom",
      "ip_count": 1,
      "unique_ips": [
        "183.103.217.251"
      ],
      "countries": [
        "KR"
      ],
      "top_country": "KR",
      "avg_abuse_score": 100,
      "max_abuse_score": 100,
      "total_reports": 0,
      "tor_count": 0,
      "proxy_count": 0,
      "vpn_count": 0,
      "anon_count": 0,
      "high_risk_count": 0,
      "critical_count": 0,
      "risk_tier": "HIGH",
      "tags": [
        "high-abuse"
      ],
      "first_seen": "2026-06-08T18:30:58Z",
      "last_seen": "2026-06-08T18:30:58Z",
      "isps": [
        "Korea Telecom"
      ]
    },
    {
      "asn": "AS17621",
      "asn_name": "China Unicom Shanghai network",
      "ip_count": 1,
      "unique_ips": [
        "106.75.227.248"
      ],
      "countries": [
        "CN"
      ],
      "top_country": "CN",
      "avg_abuse_score": 100,
      "max_abuse_score": 100,
      "total_reports": 0,
      "tor_count": 0,
      "proxy_count": 0,
      "vpn_count": 0,
      "anon_count": 0,
      "high_risk_count": 0,
      "critical_count": 0,
      "risk_tier": "HIGH",
      "tags": [
        "high-abuse"
      ],
      "first_seen": "2026-06-08T18:30:58Z",
      "last_seen": "2026-06-08T18:30:58Z",
      "isps": [
        "Shanghai UCloud Information Technology Company Limited"
      ]
    },
    {
      "asn": "AS133542",
      "asn_name": "Net Vision",
      "ip_count": 1,
      "unique_ips": [
        "103.114.254.46"
      ],
      "countries": [
        "BD"
      ],
      "top_country": "BD",
      "avg_abuse_score": 77,
      "max_abuse_score": 77,
      "total_reports": 0,
      "tor_count": 0,
      "proxy_count": 0,
      "vpn_count": 0,
      "anon_count": 0,
      "high_risk_count": 0,
      "critical_count": 0,
      "risk_tier": "MEDIUM",
      "tags": [],
      "first_seen": "2026-06-08T18:31:01Z",
      "last_seen": "2026-06-08T18:31:01Z",
      "isps": [
        "MS NETVISION"
      ]
    },
    {
      "asn": "AS7713",
      "asn_name": "PT Telekomunikasi Indonesia",
      "ip_count": 1,
      "unique_ips": [
        "36.94.123.233"
      ],
      "countries": [
        "ID"
      ],
      "top_country": "ID",
      "avg_abuse_score": 25,
      "max_abuse_score": 25,
      "total_reports": 0,
      "tor_count": 0,
      "proxy_count": 0,
      "vpn_count": 0,
      "anon_count": 0,
      "high_risk_count": 0,
      "critical_count": 0,
      "risk_tier": "LOW",
      "tags": [],
      "first_seen": "2026-06-08T18:31:03Z",
      "last_seen": "2026-06-08T18:31:03Z",
      "isps": [
        "PT Telekomunikasi Indonesia"
      ]
    },
    {
      "asn": "AS14061",
      "asn_name": "DigitalOcean, LLC",
      "ip_count": 1,
      "unique_ips": [
        "128.199.25.179"
      ],
      "countries": [
        "IN"
      ],
      "top_country": "IN",
      "avg_abuse_score": 100,
      "max_abuse_score": 100,
      "total_reports": 0,
      "tor_count": 0,
      "proxy_count": 0,
      "vpn_count": 0,
      "anon_count": 0,
      "high_risk_count": 0,
      "critical_count": 0,
      "risk_tier": "HIGH",
      "tags": [
        "high-abuse"
      ],
      "first_seen": "2026-06-08T18:30:56Z",
      "last_seen": "2026-06-08T18:30:56Z",
      "isps": [
        "DigitalOcean, LLC"
      ]
    },
    {
      "asn": "AS150436",
      "asn_name": "Byteplus Pte. Ltd.",
      "ip_count": 1,
      "unique_ips": [
        "150.5.141.198"
      ],
      "countries": [
        "HK"
      ],
      "top_country": "HK",
      "avg_abuse_score": 100,
      "max_abuse_score": 100,
      "total_reports": 0,
      "tor_count": 0,
      "proxy_count": 0,
      "vpn_count": 0,
      "anon_count": 0,
      "high_risk_count": 0,
      "critical_count": 0,
      "risk_tier": "HIGH",
      "tags": [
        "high-abuse"
      ],
      "first_seen": "2026-06-08T18:30:56Z",
      "last_seen": "2026-06-08T18:30:56Z",
      "isps": [
        "BYTEPLUS"
      ]
    },
    {
      "asn": "AS45102",
      "asn_name": "Alibaba (US) Technology Co., Ltd.",
      "ip_count": 1,
      "unique_ips": [
        "8.222.128.242"
      ],
      "countries": [
        "SG"
      ],
      "top_country": "SG",
      "avg_abuse_score": 100,
      "max_abuse_score": 100,
      "total_reports": 0,
      "tor_count": 0,
      "proxy_count": 0,
      "vpn_count": 0,
      "anon_count": 0,
      "high_risk_count": 0,
      "critical_count": 0,
      "risk_tier": "HIGH",
      "tags": [
        "high-abuse"
      ],
      "first_seen": "2026-06-08T18:30:57Z",
      "last_seen": "2026-06-08T18:30:57Z",
      "isps": [
        "Alibaba Cloud (Singapore) Private Limited"
      ]
    }
  ]
}