{
  "generated_at": "2026-04-18T02:43:13Z",
  "total_attempts": 3,
  "unique_pairs": 3,
  "unique_usernames": 3,
  "unique_passwords": 3,
  "top_usernames": [
    {
      "username": "admin",
      "count": 1
    },
    {
      "username": "orangepi",
      "count": 1
    },
    {
      "username": "root",
      "count": 1
    }
  ],
  "top_passwords": [
    {
      "password": "admin",
      "count": 1
    },
    {
      "password": "orangepi",
      "count": 1
    },
    {
      "password": "P",
      "count": 1
    }
  ],
  "top_pairs": [
    {
      "username": "admin",
      "password": "admin",
      "count": 1
    },
    {
      "username": "orangepi",
      "password": "orangepi",
      "count": 1
    },
    {
      "username": "root",
      "password": "P",
      "count": 1
    }
  ],
  "success_pairs": [
    {
      "username": "root",
      "password": "P",
      "src_ip": "2.26.86.54",
      "timestamp": "2026-04-18T00:45:05.577965Z"
    }
  ]
}