{
  "generated_at": "2026-03-26T16:58:16Z",
  "total_attempts": 28,
  "unique_pairs": 23,
  "unique_usernames": 18,
  "unique_passwords": 22,
  "top_usernames": [
    {
      "username": "root",
      "count": 5
    },
    {
      "username": "GET / HTTP/1.1",
      "count": 2
    },
    {
      "username": "User-Agent: visionheight.com/scan Mozilla/5.0 (Macintosh; Intel Mac OS X 10_15_7) Chrome/126.0.0.0 Safari/537.36",
      "count": 2
    },
    {
      "username": "Accept-Encoding: gzip",
      "count": 2
    },
    {
      "username": "345gs5662d34",
      "count": 2
    },
    {
      "username": "user",
      "count": 2
    },
    {
      "username": "Guest",
      "count": 2
    },
    {
      "username": "Nobody",
      "count": 1
    },
    {
      "username": "sshd",
      "count": 1
    },
    {
      "username": "Blank",
      "count": 1
    }
  ],
  "top_passwords": [
    {
      "password": "Host: 13.235.92.17:23",
      "count": 2
    },
    {
      "password": "Accept: */*",
      "count": 2
    },
    {
      "password": "",
      "count": 2
    },
    {
      "password": "qwerty123456",
      "count": 2
    },
    {
      "password": "345gs5662d34",
      "count": 2
    },
    {
      "password": "3245gs5662d34",
      "count": 2
    },
    {
      "password": "techsupport",
      "count": 1
    },
    {
      "password": "12345",
      "count": 1
    },
    {
      "password": "pass",
      "count": 1
    },
    {
      "password": "111111",
      "count": 1
    }
  ],
  "top_pairs": [
    {
      "username": "GET / HTTP/1.1",
      "password": "Host: 13.235.92.17:23",
      "count": 2
    },
    {
      "username": "User-Agent: visionheight.com/scan Mozilla/5.0 (Macintosh; Intel Mac OS X 10_15_7) Chrome/126.0.0.0 Safari/537.36",
      "password": "Accept: */*",
      "count": 2
    },
    {
      "username": "Accept-Encoding: gzip",
      "password": "",
      "count": 2
    },
    {
      "username": "345gs5662d34",
      "password": "345gs5662d34",
      "count": 2
    },
    {
      "username": "root",
      "password": "3245gs5662d34",
      "count": 2
    },
    {
      "username": "Nobody",
      "password": "techsupport",
      "count": 1
    },
    {
      "username": "sshd",
      "password": "12345",
      "count": 1
    },
    {
      "username": "Blank",
      "password": "pass",
      "count": 1
    },
    {
      "username": "Test",
      "password": "qwerty123456",
      "count": 1
    },
    {
      "username": "root",
      "password": "111111",
      "count": 1
    }
  ],
  "success_pairs": [
    {
      "username": "root",
      "password": "111111",
      "src_ip": "49.124.153.46",
      "timestamp": "2026-03-26T15:38:05.078168Z"
    },
    {
      "username": "root",
      "password": "lekhraj",
      "src_ip": "101.32.128.193",
      "timestamp": "2026-03-26T15:51:26.765455Z"
    },
    {
      "username": "root",
      "password": "3245gs5662d34",
      "src_ip": "101.32.128.193",
      "timestamp": "2026-03-26T15:51:29.174182Z"
    },
    {
      "username": "root",
      "password": "Qwerty12345",
      "src_ip": "103.171.69.82",
      "timestamp": "2026-03-26T16:30:59.981940Z"
    },
    {
      "username": "root",
      "password": "3245gs5662d34",
      "src_ip": "103.171.69.82",
      "timestamp": "2026-03-26T16:31:02.098413Z"
    }
  ]
}