{
  "generated_at": "2026-05-30T19:21:50Z",
  "threshold_used": 25,
  "total_cases_in": 22,
  "confirmed_threats": 16,
  "flagged_as_fp": 6,
  "fp_rate": 0.2727,
  "fp_cases": [
    {
      "case_id": "IR-756edef754ec",
      "src_ip": "54.186.216.0",
      "reason": "AbuseIPDB score 21 below threshold 25"
    },
    {
      "case_id": "IR-970ad5908f49",
      "src_ip": "84.17.55.229",
      "reason": "Mass-scanner pattern: no commands, no downloads, \u22642 login attempts"
    },
    {
      "case_id": "IR-ab5ae6e08481",
      "src_ip": "84.17.55.229",
      "reason": "Mass-scanner pattern: no commands, no downloads, \u22642 login attempts"
    },
    {
      "case_id": "IR-ea75ab023a8b",
      "src_ip": "84.17.55.229",
      "reason": "Mass-scanner pattern: no commands, no downloads, \u22642 login attempts"
    },
    {
      "case_id": "IR-f703eca20724",
      "src_ip": "84.17.55.229",
      "reason": "Mass-scanner pattern: no commands, no downloads, \u22642 login attempts"
    },
    {
      "case_id": "IR-be68ff586b88",
      "src_ip": "132.196.32.48",
      "reason": "AbuseIPDB score 17 below threshold 25"
    }
  ],
  "clean_cases": [
    "IR-c59d8254f8c7",
    "IR-7f26a4ba337d",
    "IR-e2e44aa98f7c",
    "IR-1f2f6e62894f",
    "IR-3b1e266424ae",
    "IR-e6a9f0bb570a",
    "IR-7e5fc82a1096",
    "IR-de8c79002bdd",
    "IR-609712be3d0e",
    "IR-ddcc32dd6563",
    "IR-69b366d87255",
    "IR-5baeb27b93c4",
    "IR-ec9a49b336dc",
    "IR-09e0968da487",
    "IR-236fd39e2f87",
    "IR-458d69c472fd"
  ]
}